MANIFEST.in
README.md
requirements.txt
setup.py
reveal_user_annotation/__init__.py
reveal_user_annotation.egg-info/PKG-INFO
reveal_user_annotation.egg-info/SOURCES.txt
reveal_user_annotation.egg-info/dependency_links.txt
reveal_user_annotation.egg-info/entry_points.txt
reveal_user_annotation.egg-info/requires.txt
reveal_user_annotation.egg-info/top_level.txt
reveal_user_annotation/common/__init__.py
reveal_user_annotation/common/config_package.py
reveal_user_annotation/common/datarw.py
reveal_user_annotation/entry_points/__init__.py
reveal_user_annotation/entry_points/extract_twitter_list_keywords.py
reveal_user_annotation/entry_points/store_snow_tweets_in_mongo.py
reveal_user_annotation/mongo/__init__.py
reveal_user_annotation/mongo/mongo_util.py
reveal_user_annotation/mongo/preprocess_data.py
reveal_user_annotation/mongo/store_snow_data.py
reveal_user_annotation/pserver/__init__.py
reveal_user_annotation/pserver/request.py
reveal_user_annotation/rabbitmq/__init__.py
reveal_user_annotation/rabbitmq/rabbitmq_util.py
reveal_user_annotation/text/__init__.py
reveal_user_annotation/text/clean_text.py
reveal_user_annotation/text/map_data.py
reveal_user_annotation/text/text_util.py
reveal_user_annotation/text/res/stopwords/deep_twitter_diving_stop-words.txt
reveal_user_annotation/text/res/stopwords/stack_overflow_stopwords.txt
reveal_user_annotation/text/res/stopwords/stop-words_english_1_en.txt
reveal_user_annotation/text/res/stopwords/stop-words_english_2_en.txt
reveal_user_annotation/text/res/stopwords/stop-words_english_3_en.txt
reveal_user_annotation/text/res/stopwords/stop-words_english_4_google_en.txt
reveal_user_annotation/text/res/stopwords/stop-words_english_5_en.txt
reveal_user_annotation/text/res/stopwords/stop-words_english_6_en.txt
reveal_user_annotation/twitter/__init__.py
reveal_user_annotation/twitter/clean_twitter_list.py
reveal_user_annotation/twitter/manage_resources.py
reveal_user_annotation/twitter/twitter_util.py
reveal_user_annotation/twitter/user_annotate.py
reveal_user_annotation/twitter/user_lookup.py
reveal_user_annotation/twitter/res/topics/attribute_set.txt
reveal_user_annotation/twitter/res/topics/geographical_set.txt
reveal_user_annotation/twitter/res/topics/sport_set.txt
