Metadata-Version: 1.1
Name: reveal-user-annotation
Version: 0.2.2
Summary: Utility methods for generating labels for Twitter users and handling their storage and retrieval
Home-page: https://github.com/MKLab-ITI/reveal-user-annotation
Author: Georgios Rizos
Author-email: georgerizos@iti.gr
License: Apache
Keywords: online-social-network user-annotation twitter-list-crowdsourcing Reveal-FP7
Platform: UNKNOWN
Classifier: Development Status :: 2 - Pre-Alpha
Classifier: Intended Audience :: Science/Research
Classifier: License :: OSI Approved :: Apache Software License
Classifier: Natural Language :: English
Classifier: Operating System :: Unix
Classifier: Programming Language :: Python
Classifier: Programming Language :: Python :: 3
Classifier: Programming Language :: Python :: 3.4
Classifier: Programming Language :: Python :: 3 :: Only
Classifier: Programming Language :: Python :: Implementation
Classifier: Programming Language :: Python :: Implementation :: CPython
Classifier: Topic :: Scientific/Engineering :: Information Analysis
